{
  "name": "Nodejs accelerator",
  "description": "This is a nodejs accelerator",
  "variables" : [
  {
    "workflowPath": ".github/workflows/deploy.yml",
    "variables": [
      {
        "name": "RESOURCE_NAME",
        "description": "The name of the resource"
      },
      {
        "name": "CONNECTION_ID",
        "description": "The connection id"
      }
      ]
  }
  ],
  "secrets" : [
    {
      "name": "SECRET_1",
      "description": "The value of SECRET1"
    },
    {
      "name": "SECRET_2",
      "description": "The value of SECRET2"
    }
    ]
}
